staplechain/__init__.py
staplechain/encoding.py
staplechain/shims/openai.py
staplechain/staple.py
staplechain/steganography.py
staplechain-0.1.0.dist-info/LICENSE
staplechain-0.1.0.dist-info/METADATA
staplechain-0.1.0.dist-info/WHEEL
staplechain-0.1.0.dist-info/RECORD
