Metadata-Version: 2.1
Name: staplechain
Version: 0.1.0
Summary: Signed in-band annotations for language model outputs
License: MIT
Author: Kevin Liu
Author-email: kevin@kliu.io
Requires-Python: >=3.8,<4.0
Classifier: License :: OSI Approved :: MIT License
Classifier: Programming Language :: Python :: 3
Classifier: Programming Language :: Python :: 3.8
Classifier: Programming Language :: Python :: 3.9
Classifier: Programming Language :: Python :: 3.10
Classifier: Programming Language :: Python :: 3.11
Requires-Dist: Brotli (>=1.0.9,<2.0.0)
Requires-Dist: openai (>=0.27.5,<0.28.0)
Requires-Dist: pydantic (>=1.10.7,<2.0.0)
